{
  "loader": "forge:separate-perspective",
  "gui_light": "front",
  "base": {
    "parent": "anticlimacticlagacy:item/infernal_shield_item"
  },
  "perspectives": {
    "first_person_right_hand": {
      "parent": "anticlimacticlagacy:item/infernal_shield_blocking_model"
    },
    "first_person_left_hand": {
      "parent": "anticlimacticlagacy:item/infernal_shield_blocking_model"
    },
    "third_person_right_hand": {
      "parent": "anticlimacticlagacy:item/infernal_shield_blocking_model"
    },
    "third_person_left_hand": {
      "parent": "anticlimacticlagacy:item/infernal_shield_blocking_model"
    },
    "head": {
      "parent": "anticlimacticlagacy:item/infernal_shield_blocking_model"
    }
  }
}